fastprop/__init__.py
fastprop/data.py
fastprop/defaults.py
fastprop/descriptors.py
fastprop/io.py
fastprop/metrics.py
fastprop/model.py
fastprop/cli/__init__.py
fastprop/cli/base.py
fastprop/cli/predict.py
fastprop/cli/shap.py
fastprop/cli/train.py
fastprop-1.2.2.dist-info/licenses/LICENSE
fastprop-1.2.2.dist-info/METADATA
fastprop-1.2.2.dist-info/WHEEL
fastprop-1.2.2.dist-info/entry_points.txt
fastprop-1.2.2.dist-info/top_level.txt
fastprop-1.2.2.dist-info/RECORD
