Metadata-Version: 2.4
Name: fastprop
Version: 1.2.2
Summary: Fast Molecular Property Prediction with mordredcommunity
Author: Jackson Burns
License: MIT
Project-URL: Homepage, https://github.com/JacksonBurns/fastprop
Classifier: Programming Language :: Python :: 3
Requires-Python: >=3.8
License-File: LICENSE
Requires-Dist: pyyaml
Requires-Dist: lightning
Requires-Dist: torch>=1.13
Requires-Dist: mordredcommunity
Requires-Dist: astartes[molecules]
Requires-Dist: tensorboard
Requires-Dist: psutil
Requires-Dist: polars
Requires-Dist: pandas
Requires-Dist: pyarrow
Requires-Dist: numpy
Provides-Extra: dev
Requires-Dist: black; extra == "dev"
Requires-Dist: isort; extra == "dev"
Requires-Dist: pytest; extra == "dev"
Requires-Dist: pytest-cov; extra == "dev"
Provides-Extra: hopt
Requires-Dist: ray[train]; extra == "hopt"
Requires-Dist: optuna; extra == "hopt"
Provides-Extra: shap
Requires-Dist: shap; extra == "shap"
Requires-Dist: matplotlib; extra == "shap"
Provides-Extra: bmark
Requires-Dist: py2opsin; extra == "bmark"
Dynamic: license-file
